README.md
setup.py
masonite/contrib/cloudinary/__init__.py
masonite/contrib/cloudinary/drivers/UploadCloudinaryDriver.py
masonite/contrib/cloudinary/drivers/__init__.py
masonite/contrib/cloudinary/providers/CloudinaryProvider.py
masonite/contrib/cloudinary/providers/__init__.py
masonite_cloudinary_driver.egg-info/PKG-INFO
masonite_cloudinary_driver.egg-info/SOURCES.txt
masonite_cloudinary_driver.egg-info/dependency_links.txt
masonite_cloudinary_driver.egg-info/requires.txt
masonite_cloudinary_driver.egg-info/top_level.txt