Metadata-Version: 1.0
Name: masonite-cloudinary-driver
Version: 1.0.0
Summary: Cloudinary Upload Driver for the Masonite framework
Home-page: https://github.com/vaibhavmule/masonite-cloudinary-driver
Author: Vaibhav Mule
Author-email: vaibhavmule135@gmail.com
License: UNKNOWN
Keywords: python web framework,python3,masonite,cloudinary
Platform: UNKNOWN
